Si7021-0.1.1.dist-info/DESCRIPTION.rst
Si7021-0.1.1.dist-info/METADATA
Si7021-0.1.1.dist-info/RECORD
Si7021-0.1.1.dist-info/WHEEL
Si7021-0.1.1.dist-info/metadata.json
Si7021-0.1.1.dist-info/top_level.txt
Si7021-0.1.1.dist-info/zip-safe
si7021/__init__.py
