Metadata-Version: 2.0
Name: Si7021
Version: 0.1.1
Summary: Driver for the Si7021 humidity and temperature sensor
Home-page: https://github.com/herm/Si7021
Author: Hermann Kraus
Author-email: hermann.kraus@gmail.com
License: MIT
Platform: UNKNOWN
Classifier: Development Status :: 4 - Beta
Classifier: Intended Audience :: Developers
Classifier: Operating System :: POSIX :: Linux
Classifier: Programming Language :: Python :: 2.6
Classifier: Programming Language :: Python :: 2.7
Classifier: Programming Language :: Python :: 3
Classifier: License :: OSI Approved :: MIT License
Classifier: Topic :: System :: Hardware
Classifier: Topic :: Software Development :: Embedded Systems
